rwa_tools/__init__.py
rwa_tools/graph_transform.py
rwa_tools/hamiltonian_symbolic.py
rwa_tools/py.typed
rwa_tools/transform.py
rwa_tools-0.1.3.dist-info/METADATA
rwa_tools-0.1.3.dist-info/WHEEL
rwa_tools-0.1.3.dist-info/licenses/LICENSE
rwa_tools-0.1.3.dist-info/RECORD
