Metadata-Version: 2.4
Name: rwa-tools
Version: 0.1.3
Summary: Add your description here
Author-email: ograsdijk <o.grasdijk@gmail.com>
License-Expression: MIT
License-File: LICENSE
Requires-Python: >=3.11
Requires-Dist: networkx>=3.5
Requires-Dist: sympy>=1.14.0
